ficamp/__init__.py
ficamp/__main__.py
ficamp/classifier/__init__.py
ficamp/classifier/google_apis.py
ficamp/classifier/infer.py
ficamp/classifier/keywords.py
ficamp/classifier/preprocessing.py
ficamp/data/.gitkeep
ficamp/datastructures.py
ficamp/parsers/abn.py
ficamp/parsers/bbva.py
ficamp/parsers/bsabadell.py
ficamp/parsers/caixabank.py
ficamp/parsers/enums.py
ficamp/parsers/protocols.py
ficamp/py.typed
ficamp/sinks/protocols.py
ficamp-0.13.0.dist-info/LICENSE
ficamp-0.13.0.dist-info/METADATA
ficamp-0.13.0.dist-info/WHEEL
ficamp-0.13.0.dist-info/RECORD
